[{"verse":1,"marker":1,"refs":"Job 7:1.; Job 14:1."},{"verse":5,"marker":2,"refs":"1 Paralipomenon 29:15."},{"verse":6,"marker":3,"refs":"Isaias 22:13.; Isaias 56:12.; 1 Corinthians 15:32."},{"verse":13,"marker":4,"refs":"Matthew 27:42."},{"verse":14,"marker":5,"refs":"Psalm 21:9."},{"verse":18,"marker":6,"refs":"Jeremias 11:19."},{"verse":20,"marker":7,"refs":"Jeremias 11:19."},{"verse":23,"marker":8,"refs":"Genesis 1:27.; Genesis 2:7.; Genesis 5:1.; Ecclesiasticus 17:1."},{"verse":24,"marker":9,"refs":"Genesis 3:1."}]