{"pericopes":[{"verseRef":"Leviticus 22:1-16","startVerse":1,"endVerse":16,"pericopeTitle":"SACRIFICIAL BANQUETS","overview":null,"entries":[{"subVerse":"22:14","subVerseNum":14,"source":"accs","author":"St. Jerome","date":"c. 347–420","title":"REVERENCE FOR THE EUCHARIST.","body":"At the end, it is stated, If a man eats of the sanctified things through ignorance, iniquity and wickedness are laid at his feet, and he shall be bound by a vow. Thus also the apostle teaches us that we are to eat the Eucharist of the Lord with caution, lest we eat to our condemnation and judgment.{fn:0} If ignorance is condemned under the law, how much more will full knowledge be condemned according to the gospel? {fn:1}","citation":"Against the Pelagians 1.34","footnotes":[{"type":"scripture","text":"1 Corinthians 11:28-29."},{"type":"series","text":"FC 53:284."}]}]},{"verseRef":"Leviticus 22:17-33","startVerse":17,"endVerse":33,"pericopeTitle":"UNACCEPTABLE VICTIMS","overview":null,"entries":[{"subVerse":"22:27","subVerseNum":27,"source":"accs","author":"St. Clement of Alexandria","date":"c. 150–c. 215","title":"KINDNESS EVEN TO BEASTS.","body":"Scripture says, At least grant the offspring to its mother for its first seven days. For if nothing comes to be without reason and milk flows in the mothers for the nourishment of the offspring, then in taking the offspring away from the providential endowment of the milk, a person is doing violence to nature. So Greeks and anyone else who runs the law down ought to blush for shame if the law is generous over irrational beasts. Yet some people actually expose human offspring to abortive death. By prophetic authority the law has for a long time cut short their ferocity through this commandment of which we have been speaking. For if the law refuses to allow the offspring of irrational creatures to be separated from their mother before taking milk, it is far more forceful in preparing human beings against that cruel, uncivilized view [exposure to death of infants]. If they ignore nature, at least they may not ignore the lessons of the law. {fn:0}","citation":"Stromateis 2.92.2-4","footnotes":[{"type":"series","text":"FC 85:219."}]}]}],"verseEntryCounts":{"14":1,"27":1},"totalEntries":2}