{"pericopes":[{"verseRef":"Leviticus 5:14-6:7","startVerse":14,"endVerse":7,"pericopeTitle":"GUILT OFFERINGS","overview":null,"entries":[{"subVerse":"6:3","subVerseNum":3,"source":"accs","author":"St. Augustine of Hippo","date":"354–430","title":"THE LAW TEACHES AND BINDS US.","body":"Shall we therefore say that when it is written that whoever finds another man’s property of any kind that has been lost, should return it to him who has lost it, doesn’t pertain to us? Do not many other like things pertain whereby people learn to live piously and uprightly? Isn’t especially the Decalogue itself, which is contained in those two tables of stone, apart from the carnal observance of the sabbath, which signifies spiritual sanctification and rest? {fn:0}","citation":"Against Two Letters of the Pelagians 3.10","isDocument":false,"footnotes":[{"type":"series","text":"NPNF 1 5:406."}],"fkbChapter":null},{"subVerse":"6:5","subVerseNum":5,"source":"accs","author":"Pope St. Gregory I","date":"c. 540–604","title":"THE NEW TESTAMENT MORE DEMANDING THAN THE OLD.","body":"Some people consider the commandments of the Old Testament stricter than those of the New, but they are deceived by such a shortsighted interpretation. In the former theft, not miserliness, is punished; wrongful taking of property is punished in the latter by fourfold restitution. In this place the rich man is not censured for having taken away someone else’s property but for not having sufficiently given away his own.{fn:0} {fn:1}","citation":"Homily 40","isDocument":false,"footnotes":[{"type":"scripture","text":"Mark 10:1-23."},{"type":"series","text":"CS 123:374-75."}],"fkbChapter":null}]}],"verseEntryCounts":{"3":1,"5":1},"totalEntries":2}