[{"verse":5,"marker":1,"refs":"Isaias 53:9.; 1 Peter 2:22."},{"verse":8,"marker":2,"refs":"John 8:44."},{"verse":11,"marker":3,"refs":"John 13:34.; John 15:12."},{"verse":12,"marker":4,"refs":"Genesis 4:8."},{"verse":14,"marker":5,"refs":"Leviticus 19:17.; 1 John 2:10."},{"verse":16,"marker":6,"refs":"John 15:13."},{"verse":17,"marker":7,"refs":"Luke 3:11.; James 2:15."},{"verse":22,"marker":8,"refs":"Matthew 21:22."},{"verse":23,"marker":9,"refs":"John 6:29.; John 17:2."},{"verse":24,"marker":10,"refs":"John 13:34.; John 15:12."}]