[{"verse":26,"text":"Some have supposed that it was the road, not Gaza itself, which was ‘deserted’; but it is possible that the old Gaza, destroyed in 96b.c., is here distinguished from the new Gaza, built in 58 b.c., and destroyed in a.d. 65."},{"verse":33,"text":"vv. 32, 33: Is 53.7. The Hebrew differs in several points from the text of the Septuagint, which is here quoted. Nor is the meaning of the Greek here beyond dispute; some would render ‘his condemnation’ instead of ‘his rights’, and ‘his posterity’ instead of ‘his age’."},{"verse":37,"text":"This verse is wanting in some of the Greek, and also in some of the Latin manuscripts."}]