{
  "chapter": 6,
  "footnotes": [
    {
      "verse": 3,
      "text": "St. Paul alludes to the manner in which Baptism was ordinarily conferred in the primitive Church, by immersion. The descent into the water is suggestive of the descent of the body into the grave, and the ascent is suggestive of the resurrection to a new life. St. Paul obviously sees more than a mere symbol in the rite of Baptism. As a result of it we are incorporated into Christ's mystical body and live a new life."
    },
    {
      "verse": 6,
      "text": "<i>The body of sin:</i> some, with St. John Chrysostom, take this expression to indicate sin in general, and others understand it of the body inasmuch as it is subject to concupiscence and is the instrument of sin. As such it is destroyed, i.e., reduced to impotence, so that we are no longer slaves to its evil inclinations."
    }
  ]
}