[{"verse":2,"marker":1,"refs":"2 Esdras 8:4."},{"verse":4,"marker":2,"refs":"Luke 11:46.; Acts 15:10."},{"verse":5,"marker":3,"refs":"Numbers 15:38.; Deuteronomy 6:8.; Deuteronomy 22:12."},{"verse":6,"marker":4,"refs":"Mark 12:39.; Luke 11:43.; Luke 20:40."},{"verse":8,"marker":5,"refs":"James 3:1."},{"verse":9,"marker":6,"refs":"Malachias 1:6."},{"verse":12,"marker":7,"refs":"Luke 14:11.; Luke 18:14."},{"verse":14,"marker":8,"refs":"Mark 12:40.; Luke 20:47."},{"verse":23,"marker":9,"refs":"Luke 11:42.; Micheas 6:8.; Zacharias 7:9."},{"verse":33,"marker":10,"refs":"Matthew 3:7."},{"verse":35,"marker":11,"refs":"Genesis 4:8.; Hebrews 11:4.; 2 Paralipomenon 24:22."},{"verse":37,"marker":12,"refs":"Luke 13:34."}]