{
  "chapter": 25,
  "sections": [
    {
      "startVerse": 17,
      "endVerse": 27,
      "heading": "4. Imprisonment in Palestine 21, 17 -- 26, 32 (continued)",
      "paragraphs": [
        "<b><i>25,</i> 1-12: Festus.</b> The two years' inactivity had not lessened the Jew's animosity against St. Paul. Backed by a shouting crowd, they had at first tried to overawe the new procurator and force him to condemn St. Paul at once (<i>25,</i> 15 f). Failing this, they wanted him to order the trial held at Jerusalem. <b>9.</b> The injustice of this request is indicated by his motive which was to begin his term of office with the good will of the Jews. <b>11.</b> St. Paul knew the hopelessness of justice in such a trial and also perhaps the plots against his life. Once he exercised his right as a Roman citizen to be tried before the Emperor at Rome, Festus had to admit the appeal.",
        "<b><i>25,</i> 13-27: Agrippa. 13.</b> <i>Agrippa</i> was the son of Herod Agrippa I, who had persecuted the Church (Acts <i>12</i>), and the great-grandson of Herod the Great. He had received Chalchis, to the north of Palestine, from the Emperor Claudius and later was given Batanea and the vicinity. He had authority over the Jews in religious matters. During the Jewish war he sided with the Romans. His sister Bernice lived with him after the death of her first husband, Herod of Chalcis, and rumor accused them of incestuous intimacy. Then she married Polemon, king of Pontus, but later king merely of a small section of northwestern Cilicia; but she soon left him and returned to her brother. She found favor with both Vespasian and Titus during the Jewish War, and Titus would have married her in Rome, had it not been for the popular outcry. <b>20.</b> In reality he was afraid of the Jews. <b>21.</b> He seems aware that he has put himself in a false position by forcing St. Paul to appeal instead of releasing him."
      ]
    }
  ]
}