[{"verse":3,"text":"The phrase ‘spiritus intelligentiæ meæ’ means ‘the spirit of my understanding.’ However, in English, we tend to phrase that idea in this way: ‘my spirit of understanding.’ It could be phrased either way."},{"verse":7,"text":"These two verses refer to the Antichrist, in his attempt at a false ascension to Heaven."},{"verse":24,"text":"This last phrase can also be translated as: ‘will fall in a flying fortress.’ Such a translation implies an eschatological meaning to this passage, a passage which in my view refers to the Antichrist."}]